royalnet_telethon/__init__.py
royalnet_telethon/bullet/contents/__init__.py
royalnet_telethon/bullet/projectiles/_imports.py
royalnet_telethon/bullet/projectiles/message.py
royalnet_telethon/formatting.py
royalnet_telethon/pda.py
royalnet_telethon-6.6.2.dist-info/LICENSE.txt
royalnet_telethon-6.6.2.dist-info/WHEEL
royalnet_telethon-6.6.2.dist-info/METADATA
royalnet_telethon-6.6.2.dist-info/RECORD
