Metadata-Version: 2.1
Name: royalnet-telethon
Version: 6.6.2
Summary: A Telethon-based frontend for the royalnet.engineer module.
Home-page: https://github.com/Steffo99/royalnet-telethon
License: AGPL-3.0-or-later
Keywords: royalnet
Author: Stefano Pigozzi
Author-email: me@steffo.eu
Requires-Python: >=3.8,<4.0
Classifier: Development Status :: 3 - Alpha
Classifier: Intended Audience :: Developers
Classifier: License :: OSI Approved :: GNU Affero General Public License v3 or later (AGPLv3+)
Classifier: Operating System :: OS Independent
Classifier: Programming Language :: Python :: 3
Classifier: Programming Language :: Python :: 3.10
Classifier: Programming Language :: Python :: 3.8
Classifier: Programming Language :: Python :: 3.9
Requires-Dist: Telethon (>=1.21.1,<2.0.0)
Requires-Dist: click (>=7.1.2,<8.0.0)
Requires-Dist: royalnet (>=6.6.0,<6.7.0)
Project-URL: Documentation, https://royalnet-telethon.readthedocs.io/
Project-URL: Repository, https://github.com/Steffo99/royalnet-telethon
